imprimir/__init__.py
imprimir/imprime.py
impressoramanual-1.0.0.dist-info/LICENCE.txt
impressoramanual-1.0.0.dist-info/METADATA
impressoramanual-1.0.0.dist-info/WHEEL
impressoramanual-1.0.0.dist-info/top_level.txt
impressoramanual-1.0.0.dist-info/RECORD
