Metadata-Version: 2.1
Name: impressoramanual
Version: 1.0.0
Summary: ese é um projeto de impressão
Home-page: https://github.com/pypa/sampleproject
Author: developer10
Author-email: developer10@gmail.com
License: UNKNOWN
Platform: UNKNOWN
Classifier: Programming Language :: Python :: 3
Classifier: License :: OSI Approved :: MIT License
Classifier: Operating System :: OS Independent
Requires-Python: >=3.6
License-File: LICENCE.txt
